rustc_dev_t_x64_win_msvc_nightly_p9/__init__.py
rustc_dev_t_x64_win_msvc_nightly_p9/data/libicu_list-6344a36af7ea4589.rmeta
rustc_dev_t_x64_win_msvc_nightly_p9/data/librand_chacha-b1f7e7af7590eb00.rmeta
rustc_dev_t_x64_win_msvc_nightly_p9/data/libregex_syntax-83f2eab5165ac334.rmeta
rustc_dev_t_x64_win_msvc_nightly_p9/data/librustc_attr_parsing-44ed21cb58002dc9.rmeta
rustc_dev_t_x64_win_msvc_nightly_p9/data/librustc_baked_icu_data-e6d2a1669edac8ee.rmeta
rustc_dev_t_x64_win_msvc_nightly_p9/data/librustc_builtin_macros-b8dcfbfa3831c29b.rmeta
rustc_dev_t_x64_win_msvc_nightly_p9/data/librustc_codegen_llvm-df8500e51399ceaa.rmeta
rustc_dev_t_x64_win_msvc_nightly_p9/data/librustc_proc_macro-e1028f846ca76020.rmeta
rustc_dev_t_x64_win_msvc_nightly_p9/data/libruzstd-15996101d5808e44.rmeta
rustc_dev_t_x64_win_msvc_nightly_p9/data/libscoped_tls-19c5675bfa6bc9bb.rmeta
rustc_dev_t_x64_win_msvc_nightly_p9/data/libunicode_xid-99e1e30f3faa8231.rmeta
rustc_dev_t_x64_win_msvc_nightly_p9/data/unic_langid_macros_impl-d421a4d1928e2e5c.dll
rustc_dev_t_x64_win_msvc_nightly_p9/data/windows_implement-24688cbe58033ffc.dll.lib
rustc_dev_t_x64_win_msvc_nightly_p9/data/windows_interface-fa61fe6bfcbc4a3d.dll.lib
rustc_dev_t_x64_win_msvc_nightly_p9-1.91.0.dist-info/METADATA
rustc_dev_t_x64_win_msvc_nightly_p9-1.91.0.dist-info/WHEEL
rustc_dev_t_x64_win_msvc_nightly_p9-1.91.0.dist-info/top_level.txt
rustc_dev_t_x64_win_msvc_nightly_p9-1.91.0.dist-info/RECORD
